quantum_harvest/REPLAY_VISUALIZER_README.md
quantum_harvest/__init__.py
quantum_harvest/agent_v_agent_config.py
quantum_harvest/agent_v_agent_script.py
quantum_harvest/agents.py
quantum_harvest/cli.py
quantum_harvest/environment.py
quantum_harvest/game_config.py
quantum_harvest/quantum_harvest_replay_visualizer.html
quantum_harvest/replay_compression.py
quantum_harvest/run_replay_visualizer.py
quantum_harvest/starter_agent.py
quantum_harvest/training.py
quantum_harvest/utils.py
quantum_harvest/visualizer.py
quantum_harvest-1.0.3.dist-info/licenses/LICENSE
quantum_harvest-1.0.3.dist-info/METADATA
quantum_harvest-1.0.3.dist-info/WHEEL
quantum_harvest-1.0.3.dist-info/entry_points.txt
quantum_harvest-1.0.3.dist-info/top_level.txt
quantum_harvest-1.0.3.dist-info/RECORD
