Metadata-Version: 2.4
Name: quantum-harvest
Version: 1.0.3
Summary: A competitive 1v1 AI simulation game combining quantum mechanics with strategic resource management
Author-email: Tanaka Chiromo <tanakachiromo@gmail.com>
License-Expression: CC-BY-NC-4.0
Project-URL: Homepage, https://github.com/tanaka-chiromo/quantum-harvest
Project-URL: Repository, https://github.com/tanaka-chiromo/quantum-harvest.git
Project-URL: Issues, https://github.com/tanaka-chiromo/quantum-harvest/issues
Keywords: game,ai,quantum,strategy,reinforcement-learning
Classifier: Development Status :: 4 - Beta
Classifier: Intended Audience :: Developers
Classifier: Intended Audience :: Science/Research
Classifier: Operating System :: OS Independent
Classifier: Programming Language :: Python :: 3
Classifier: Programming Language :: Python :: 3.8
Classifier: Programming Language :: Python :: 3.9
Classifier: Programming Language :: Python :: 3.10
Classifier: Programming Language :: Python :: 3.11
Classifier: Programming Language :: Python :: 3.12
Classifier: Topic :: Games/Entertainment
Classifier: Topic :: Scientific/Engineering :: Artificial Intelligence
Requires-Python: >=3.8
License-File: LICENSE
Requires-Dist: numpy>=1.21.0
Requires-Dist: pygame>=2.1.0
Requires-Dist: gymnasium>=0.28.0
Provides-Extra: dev
Requires-Dist: pytest>=7.0.0; extra == "dev"
Requires-Dist: pytest-cov>=4.0.0; extra == "dev"
Requires-Dist: black>=22.0.0; extra == "dev"
Requires-Dist: flake8>=5.0.0; extra == "dev"
Requires-Dist: mypy>=1.0.0; extra == "dev"
Requires-Dist: isort>=5.0.0; extra == "dev"
Dynamic: license-file
